.installed.cfg
CHANGES.txt
LICENSE.txt
MANIFEST.in
README.txt
buildout.cfg
setup.py
docs/Makefile
docs/source/conf.py
docs/source/index.rst
repoze/__init__.py
repoze.what.plugins.hgwebdir.egg-info/PKG-INFO
repoze.what.plugins.hgwebdir.egg-info/SOURCES.txt
repoze.what.plugins.hgwebdir.egg-info/dependency_links.txt
repoze.what.plugins.hgwebdir.egg-info/namespace_packages.txt
repoze.what.plugins.hgwebdir.egg-info/not-zip-safe
repoze.what.plugins.hgwebdir.egg-info/requires.txt
repoze.what.plugins.hgwebdir.egg-info/top_level.txt
repoze/what/__init__.py
repoze/what/plugins/__init__.py
repoze/what/plugins/hgwebdir/__init__.py
repoze/what/plugins/hgwebdir/adapters.py
repoze/what/plugins/hgwebdir/middleware.py
repoze/what/plugins/hgwebdir/predicates.py
repoze/what/plugins/hgwebdir/tests.py