Metadata-Version: 1.0
Name: repoze.what.plugins.hgwebdir
Version: 0.1.1
Summary: A simple repoze.what plugin useful for Mercurial hgwebdir
Home-page: https://www.lorenzogil.com/projects/repoze.what.plugins.hgwebdir/
Author: Yaco Sistemas
Author-email: lgs@yaco.es
License: BSD-derived (http://www.repoze.org/LICENSE.txt)
Keywords: authorization web application server wsgi repoze
Platform: UNKNOWN
Classifier: Development Status :: 3 - Alpha
Classifier: Environment :: Web Environment
Classifier: Intended Audience :: Developers
Classifier: Operating System :: OS Independent
Classifier: Programming Language :: Python
Classifier: Topic :: Internet :: WWW/HTTP
Classifier: Topic :: Internet :: WWW/HTTP :: WSGI
Classifier: Topic :: Security
Classifier: Topic :: Software Development :: Libraries :: Application Frameworks
